setup.py
sayan_distributions/Binomialdistribution.py
sayan_distributions/Gaussiandistribution.py
sayan_distributions/Generaldistribution.py
sayan_distributions/__init__.py
sayan_distributions.egg-info/PKG-INFO
sayan_distributions.egg-info/SOURCES.txt
sayan_distributions.egg-info/dependency_links.txt
sayan_distributions.egg-info/not-zip-safe
sayan_distributions.egg-info/top_level.txt