Metadata-Version: 1.0
Name: sayan-distributions
Version: 1.0
Summary: Gaussian distributions
Home-page: UNKNOWN
Author: Osayanhu Imoisili
Author-email: jerryosaimo@gmail.com
License: UNKNOWN
Platform: UNKNOWN
